[[{"line_text": "", "words": [{"text": "", "left": 0, "top": 0, "width": 1306, "height": 2152}, {"text": "", "left": 36, "top": 129, "width": 1262, "height": 2013}, {"text": "", "left": 36, "top": 129, "width": 1262, "height": 2013}]}, {"line_text": "PREFEITURA DE", "words": [{"text": "", "left": 478, "top": 129, "width": 298, "height": 43}, {"text": "PREFEITURA", "left": 478, "top": 129, "width": 237, "height": 43}, {"text": "DE", "left": 728, "top": 129, "width": 48, "height": 30}]}, {"line_text": "SÃO PAULO", "words": [{"text": "", "left": 476, "top": 172, "width": 303, "height": 50}, {"text": "SÃO", "left": 476, "top": 172, "width": 112, "height": 40}, {"text": "PAULO", "left": 602, "top": 172, "width": 177, "height": 50}]}, {"line_text": "GESTÃO", "words": [{"text": "", "left": 578, "top": 225, "width": 97, "height": 16}, {"text": "GESTÃO", "left": 578, "top": 225, "width": 97, "height": 16}]}, {"line_text": "ANEXO |", "words": [{"text": "", "left": 36, "top": 301, "width": 135, "height": 26}, {"text": "ANEXO", "left": 36, "top": 301, "width": 117, "height": 26}, {"text": "|", "left": 166, "top": 302, "width": 5, "height": 24}]}, {"line_text": "FICHA DE INSCRIÇÃO", "words": [{"text": "", "left": 39, "top": 428, "width": 345, "height": 37}, {"text": "FICHA", "left": 39, "top": 433, "width": 97, "height": 26}, {"text": "DE", "left": 148, "top": 434, "width": 42, "height": 24}, {"text": "INSCRIÇÃO", "left": 204, "top": 428, "width": 180, "height": 37}]}, {"line_text": "DADOS DO PROPONENTE", "words": [{"text": "", "left": 38, "top": 565, "width": 417, "height": 26}, {"text": "DADOS", "left": 38, "top": 565, "width": 115, "height": 26}, {"text": "DO", "left": 166, "top": 565, "width": 46, "height": 26}, {"text": "PROPONENTE", "left": 226, "top": 565, "width": 229, "height": 26}]}, {"line_text": "NOME: MOOH TECH SOLUÇÕES MOBILE E SOFTWARES LTDA - EPP", "words": [{"text": "", "left": 137, "top": 619, "width": 1064, "height": 39}, {"text": "NOME:", "left": 137, "top": 631, "width": 104, "height": 26}, {"text": "MOOH", "left": 261, "top": 625, "width": 99, "height": 26}, {"text": "TECH", "left": 370, "top": 625, "width": 87, "height": 26}, {"text": "SOLUÇÕES", "left": 467, "top": 619, "width": 181, "height": 39}, {"text": "MOBILE", "left": 659, "top": 625, "width": 120, "height": 26}, {"text": "E", "left": 790, "top": 625, "width": 19, "height": 25}, {"text": "SOFTWARES", "left": 818, "top": 625, "width": 205, "height": 26}, {"text": "LTDA", "left": 1034, "top": 625, "width": 95, "height": 25}, {"text": "-", "left": 1114, "top": 615, "width": 15, "height": 47}, {"text": "EPP", "left": 1139, "top": 625, "width": 62, "height": 25}]}, {"line_text": "R.G./CNPJ: 27.355.139/0001-04", "words": [{"text": "", "left": 137, "top": 695, "width": 473, "height": 28}, {"text": "R.G./CNPJ:", "left": 137, "top": 698, "width": 169, "height": 25}, {"text": "27.355.139/0001-04", "left": 328, "top": 695, "width": 282, "height": 25}]}, {"line_text": "ENDEREÇO: RUAMADRE DE DEUS", "words": [{"text": "", "left": 137, "top": 758, "width": 571, "height": 37}, {"text": "ENDEREÇO:", "left": 137, "top": 764, "width": 193, "height": 31}, {"text": "RUAMADRE", "left": 364, "top": 759, "width": 191, "height": 25}, {"text": "DE", "left": 566, "top": 759, "width": 43, "height": 25}, {"text": "DEUS", "left": 619, "top": 758, "width": 89, "height": 26}]}, {"line_text": "NÚMERO: 66", "words": [{"text": "", "left": 137, "top": 824, "width": 213, "height": 31}, {"text": "NÚMERO:", "left": 137, "top": 824, "width": 152, "height": 31}, {"text": "66", "left": 315, "top": 827, "width": 35, "height": 25}]}, {"line_text": "COMPLEMENTO: LOJA0OOO01 SALA 110", "words": [{"text": "", "left": 136, "top": 889, "width": 602, "height": 32}, {"text": "COMPLEMENTO:", "left": 136, "top": 896, "width": 266, "height": 25}, {"text": "LOJA0OOO01", "left": 433, "top": 889, "width": 152, "height": 27}, {"text": "SALA", "left": 599, "top": 885, "width": 74, "height": 41}, {"text": "110", "left": 691, "top": 890, "width": 47, "height": 25}]}, {"line_text": "BAIRRO: RECIFE ANTIGO", "words": [{"text": "", "left": 137, "top": 955, "width": 400, "height": 32}, {"text": "BAIRRO:", "left": 137, "top": 962, "width": 132, "height": 25}, {"text": "RECIFE", "left": 290, "top": 955, "width": 116, "height": 26}, {"text": "ANTIGO", "left": 413, "top": 955, "width": 124, "height": 26}]}, {"line_text": "CEP: 50.030-110", "words": [{"text": "", "left": 136, "top": 1023, "width": 246, "height": 30}, {"text": "CEP:", "left": 136, "top": 1028, "width": 74, "height": 25}, {"text": "50.030-110", "left": 225, "top": 1023, "width": 157, "height": 25}]}, {"line_text": "MUNICÍPIO: RECIFE", "words": [{"text": "", "left": 137, "top": 1088, "width": 321, "height": 32}, {"text": "MUNICÍPIO:", "left": 137, "top": 1089, "width": 180, "height": 31}, {"text": "RECIFE", "left": 341, "top": 1088, "width": 117, "height": 27}]}, {"line_text": "UF: PE", "words": [{"text": "", "left": 137, "top": 1157, "width": 114, "height": 29}, {"text": "UF:", "left": 137, "top": 1161, "width": 48, "height": 25}, {"text": "PE", "left": 210, "top": 1157, "width": 41, "height": 25}]}, {"line_text": "DDD TELEFONE: (81)3019-1776", "words": [{"text": "", "left": 137, "top": 1220, "width": 511, "height": 33}, {"text": "DDD", "left": 137, "top": 1227, "width": 68, "height": 25}, {"text": "TELEFONE:", "left": 217, "top": 1227, "width": 181, "height": 25}, {"text": "(81)3019-1776", "left": 441, "top": 1220, "width": 207, "height": 33}]}, {"line_text": "CORREIO ELETRÔNICO DO PROPONENTE: CONTATOGQMOOHTECH.COM", "words": [{"text": "", "left": 136, "top": 1287, "width": 1162, "height": 34}, {"text": "CORREIO", "left": 136, "top": 1293, "width": 152, "height": 25}, {"text": "ELETRÔNICO", "left": 302, "top": 1287, "width": 212, "height": 31}, {"text": "DO", "left": 528, "top": 1293, "width": 46, "height": 25}, {"text": "PROPONENTE:", "left": 587, "top": 1293, "width": 238, "height": 25}, {"text": "CONTATOGQMOOHTECH.COM", "left": 835, "top": 1288, "width": 463, "height": 33}]}, {"line_text": "E, por ser expressão da verdade, declaro que li o Edital de Chamamento", "words": [{"text": "", "left": 38, "top": 1424, "width": 1177, "height": 32}, {"text": "E,", "left": 38, "top": 1425, "width": 27, "height": 29}, {"text": "por", "left": 88, "top": 1431, "width": 47, "height": 25}, {"text": "ser", "left": 153, "top": 1431, "width": 46, "height": 18}, {"text": "expressão", "left": 217, "top": 1425, "width": 151, "height": 31}, {"text": "da", "left": 388, "top": 1425, "width": 35, "height": 24}, {"text": "verdade,", "left": 443, "top": 1425, "width": 127, "height": 29}, {"text": "declaro", "left": 592, "top": 1425, "width": 107, "height": 24}, {"text": "que", "left": 719, "top": 1431, "width": 53, "height": 25}, {"text": "li", "left": 794, "top": 1425, "width": 10, "height": 24}, {"text": "o", "left": 833, "top": 1431, "width": 8, "height": 18}, {"text": "Edital", "left": 863, "top": 1425, "width": 79, "height": 24}, {"text": "de", "left": 963, "top": 1425, "width": 35, "height": 24}, {"text": "Chamamento", "left": 1018, "top": 1424, "width": 197, "height": 26}]}, {"line_text": "Público n.º 02/2017-SMG.GAB, e concordo com todos os seus termos.", "words": [{"text": "", "left": 38, "top": 1463, "width": 1041, "height": 29}, {"text": "Público", "left": 38, "top": 1463, "width": 106, "height": 25}, {"text": "n.º", "left": 157, "top": 1463, "width": 37, "height": 25}, {"text": "02/2017-SMG.GAB,", "left": 205, "top": 1463, "width": 293, "height": 29}, {"text": "e", "left": 510, "top": 1469, "width": 16, "height": 19}, {"text": "concordo", "left": 538, "top": 1463, "width": 135, "height": 25}, {"text": "com", "left": 685, "top": 1469, "width": 60, "height": 19}, {"text": "todos", "left": 757, "top": 1463, "width": 79, "height": 25}, {"text": "os", "left": 848, "top": 1469, "width": 33, "height": 19}, {"text": "seus", "left": 893, "top": 1469, "width": 68, "height": 19}, {"text": "termos.", "left": 971, "top": 1464, "width": 108, "height": 24}]}, {"line_text": "Local e data : SÃO PAULO-SP, 23 DE MAIO DE 2017", "words": [{"text": "", "left": 390, "top": 1589, "width": 767, "height": 36}, {"text": "Local", "left": 390, "top": 1596, "width": 75, "height": 24}, {"text": "e", "left": 477, "top": 1602, "width": 16, "height": 18}, {"text": "data", "left": 505, "top": 1596, "width": 62, "height": 24}, {"text": ":", "left": 585, "top": 1602, "width": 1, "height": 18}, {"text": "SÃO", "left": 594, "top": 1589, "width": 68, "height": 32}, {"text": "PAULO-SP,", "left": 673, "top": 1594, "width": 161, "height": 31}, {"text": "23", "left": 845, "top": 1595, "width": 35, "height": 25}, {"text": "DE", "left": 890, "top": 1595, "width": 43, "height": 25}, {"text": "MAIO", "left": 944, "top": 1594, "width": 80, "height": 27}, {"text": "DE", "left": 1035, "top": 1595, "width": 42, "height": 25}, {"text": "2017", "left": 1087, "top": 1595, "width": 70, "height": 25}]}, {"line_text": "EVERTON MANOEL CRUZ DA SILVA", "words": [{"text": "", "left": 549, "top": 1812, "width": 545, "height": 43}, {"text": "EVERTON", "left": 549, "top": 1829, "width": 153, "height": 26}, {"text": "MANOEL", "left": 713, "top": 1817, "width": 135, "height": 38}, {"text": "CRUZ", "left": 865, "top": 1812, "width": 83, "height": 43}, {"text": "DA", "left": 958, "top": 1829, "width": 44, "height": 26}, {"text": "SILVA", "left": 1008, "top": 1829, "width": 86, "height": 26}]}, {"line_text": "CEO", "words": [{"text": "", "left": 548, "top": 1871, "width": 69, "height": 26}, {"text": "CEO", "left": 548, "top": 1871, "width": 69, "height": 26}]}, {"line_text": "RG:0875884121", "words": [{"text": "", "left": 549, "top": 1914, "width": 228, "height": 26}, {"text": "RG:0875884121", "left": 549, "top": 1914, "width": 228, "height": 26}]}, {"line_text": "CPF:004.194.645-65", "words": [{"text": "", "left": 548, "top": 1956, "width": 294, "height": 27}, {"text": "CPF:004.194.645-65", "left": 548, "top": 1956, "width": 294, "height": 27}]}, {"line_text": "Viaduto do Chá, 15 — 8º andar — Centro — São Paulo/SP — 01002-900", "words": [{"text": "", "left": 157, "top": 2078, "width": 939, "height": 27}, {"text": "Viaduto", "left": 157, "top": 2079, "width": 102, "height": 22}, {"text": "do", "left": 270, "top": 2079, "width": 32, "height": 22}, {"text": "Chá,", "left": 313, "top": 2078, "width": 59, "height": 27}, {"text": "15", "left": 387, "top": 2079, "width": 30, "height": 22}, {"text": "—", "left": 426, "top": 2092, "width": 18, "height": 2}, {"text": "8º", "left": 453, "top": 2079, "width": 26, "height": 22}, {"text": "andar", "left": 490, "top": 2079, "width": 77, "height": 22}, {"text": "—", "left": 575, "top": 2092, "width": 17, "height": 2}, {"text": "Centro", "left": 602, "top": 2078, "width": 90, "height": 23}, {"text": "—", "left": 701, "top": 2092, "width": 18, "height": 2}, {"text": "São", "left": 728, "top": 2078, "width": 52, "height": 23}, {"text": "Paulo/SP", "left": 792, "top": 2078, "width": 123, "height": 23}, {"text": "—", "left": 925, "top": 2092, "width": 18, "height": 2}, {"text": "01002-900", "left": 952, "top": 2079, "width": 144, "height": 22}]}, {"line_text": "Tel: (11) 3113-8142 / 3113-8145", "words": [{"text": "", "left": 407, "top": 2114, "width": 438, "height": 28}, {"text": "Tel:", "left": 407, "top": 2114, "width": 47, "height": 22}, {"text": "(11)", "left": 468, "top": 2114, "width": 51, "height": 28}, {"text": "3113-8142", "left": 530, "top": 2114, "width": 144, "height": 22}, {"text": "/", "left": 684, "top": 2114, "width": 8, "height": 22}, {"text": "3113-8145", "left": 702, "top": 2114, "width": 143, "height": 22}]}]]